ProBioPred-1.0.0.data/scripts/proBioPred.py
probiopred/__init__.py
probiopred/csvToLibSVM.R
probiopred/probiopred.py
probiopred/data/models/bacillus.model
probiopred/data/models/bifidobacterium.model
probiopred/data/models/clostridium.model
probiopred/data/models/enterococcus.model
probiopred/data/models/lactobacillus.model
probiopred/data/models/lactococcus.model
probiopred/data/models/leuconostoc.model
probiopred/data/models/pediococcus.model
probiopred/data/models/streptococcus.model
probiopred/data/pro/bacillus.pfasta
probiopred/data/pro/bifidobactrium.pfasta
probiopred/data/pro/clostridium.pfasta
probiopred/data/pro/enterococcus.pfasta
probiopred/data/pro/escherichia.pfasta
probiopred/data/pro/lactobacillus.pfasta
probiopred/data/pro/lactococcus.pfasta
probiopred/data/pro/leuconostoc.pfasta
probiopred/data/pro/pediococcus.pfasta
probiopred/data/pro/streptococcus.pfasta
probiopred/data/vfdb/bacillus.pfasta
probiopred/data/vfdb/clostridium.pfasta
probiopred/data/vfdb/enterococcus.pfasta
probiopred/data/vfdb/streptococcus.pfasta
ProBioPred-1.0.0.dist-info/LICENCE
ProBioPred-1.0.0.dist-info/METADATA
ProBioPred-1.0.0.dist-info/WHEEL
ProBioPred-1.0.0.dist-info/top_level.txt
ProBioPred-1.0.0.dist-info/RECORD
