Metadata-Version: 2.1
Name: ProBioPred
Version: 1.0.0
Summary: Probiotic candidate prediction on the basis of genomic features by using Support Vector machine (SVM).
Home-page: https://github.com/microDM/ProBioPred
Maintainer: Dattatray Mongad
License: UNKNOWN
Platform: UNKNOWN
Requires-Dist: biopython
